Metadata-Version: 1.1
Name: airwing-autopublish
Version: 1.0.4
Summary: GeoServer REST Configuration
Home-page: https://github.com/surongxiang/gsconfig
Author: David Winslow, Sebastian Benthall
Author-email: hfutsrx@gmail.com
License: MIT
Keywords: GeoServer REST Configuration
Platform: UNKNOWN
Classifier: Development Status :: 4 - Beta
Classifier: Intended Audience :: Developers
Classifier: Intended Audience :: Science/Research
Classifier: License :: OSI Approved :: MIT License
Classifier: Operating System :: OS Independent
Classifier: Programming Language :: Python
Classifier: Topic :: Scientific/Engineering :: GIS
